together_gradio/__init__.py
together_gradio-0.0.1.dist-info/METADATA
together_gradio-0.0.1.dist-info/WHEEL
together_gradio-0.0.1.dist-info/RECORD
